onecc/__init__.py
onecc/errors.py
onecc/_cli/__init__.py
onecc/_cli/adapter.py
onecc/_cli/command_builder.py
onecc/_cli/onecc.py
onecc/_cli/validate.py
onecc/_fs/__init__.py
onecc/_fs/workspace.py
onecc/_fs/workspace_registry.py
onecc/commands/__init__.py
onecc/commands/import_.py
onecc/commands/optimize.py
onecc/commands/quantize.py
onecc/experimental/__init__.py
onecc/experimental/auto/__init__.py
onecc/experimental/auto/import_.py
onecc/experimental/auto/optimize.py
onecc/experimental/auto/quantize.py
onecc/models/__init__.py
onecc/models/circle.py
onecc-0.2.2.dist-info/LICENSE
onecc-0.2.2.dist-info/METADATA
onecc-0.2.2.dist-info/WHEEL
onecc-0.2.2.dist-info/top_level.txt
onecc-0.2.2.dist-info/RECORD
