Metadata-Version: 2.1
Name: onecc
Version: 0.2.2
Summary: Python package for ONE compiler
Home-page: UNKNOWN
License: UNKNOWN
Platform: UNKNOWN
License-File: LICENSE
Requires-Dist: circle-schema
Requires-Dist: h5py
